setup.py
bhg/__init__.py
bhg/db.py
bhg/graph.py
bhg/mixins.py
bhg/queryset.py
bhypergraphs.egg-info/PKG-INFO
bhypergraphs.egg-info/SOURCES.txt
bhypergraphs.egg-info/dependency_links.txt
bhypergraphs.egg-info/requires.txt
bhypergraphs.egg-info/top_level.txt