Metadata-Version: 1.0
Name: bhypergraphs
Version: 1.0.5
Summary: Hypergraphs and DB using hypergraphs
Home-page: https://bitbucket.org/blins/hypergraphs
Author: Oleg Karakin aka blins
Author-email: blins@blins.org
License: BSD
Platform: UNKNOWN
